{"match":{"startDateTime":1716636480,"chatEvents":[{"type":5,"fromHeroId":138,"toHeroId":{},"value":329},{"type":11,"fromHeroId":{},"toHeroId":{},"value":0},{"type":12,"fromHeroId":{},"toHeroId":{},"value":0},{"type":11,"fromHeroId":{},"toHeroId":{},"value":0},{"type":11,"fromHeroId":{},"toHeroId":{},"value":0},{"type":11,"fromHeroId":{},"toHeroId":{},"value":0},{"type":11,"fromHeroId":{},"toHeroId":{},"value":0},{"type":12,"fromHeroId":{},"toHeroId":{},"value":0},{"type":12,"fromHeroId":{},"toHeroId":{},"value":0},{"type":12,"fromHeroId":{},"toHeroId":{},"value":0},{"type":114,"fromHeroId":58,"toHeroId":{},"value":4},{"type":12,"fromHeroId":{},"toHeroId":{},"value":0},{"type":12,"fromHeroId":{},"toHeroId":{},"value":0},{"type":15,"fromHeroId":138,"toHeroId":{},"value":0},{"type":15,"fromHeroId":70,"toHeroId":{},"value":0},{"type":15,"fromHeroId":14,"toHeroId":{},"value":0},{"type":15,"fromHeroId":58,"toHeroId":{},"value":0},{"type":15,"fromHeroId":17,"toHeroId":{},"value":0},{"type":15,"fromHeroId":28,"toHeroId":{},"value":0},{"type":15,"fromHeroId":71,"toHeroId":{},"value":0},{"type":15,"fromHeroId":104,"toHeroId":{},"value":0},{"type":15,"fromHeroId":75,"toHeroId":{},"value":0},{"type":15,"fromHeroId":123,"toHeroId":{},"value":0}],"players":[{"steamAccountId":185908355,"heroId":70,"dotaPlus":{"level":30}},{"steamAccountId":107803494,"heroId":14,"dotaPlus":{}},{"steamAccountId":118134220,"heroId":28,"dotaPlus":{"level":17}},{"steamAccountId":101695162,"heroId":123,"dotaPlus":{"level":21}},{"steamAccountId":158847773,"heroId":58,"dotaPlus":{"level":13}},{"steamAccountId":898754153,"heroId":138,"dotaPlus":{"level":13}},{"steamAccountId":137129583,"heroId":17,"dotaPlus":{"level":29}},{"steamAccountId":129958758,"heroId":104,"dotaPlus":{"level":13}},{"steamAccountId":157475523,"heroId":71,"dotaPlus":{"level":11}},{"steamAccountId":143693439,"heroId":75,"dotaPlus":{}}]}}
