{"match":{"startDateTime":1719069840,"chatEvents":[{"type":1000,"fromHeroId":96,"toHeroId":20,"value":50},{"type":1000,"fromHeroId":126,"toHeroId":20,"value":50},{"type":1000,"fromHeroId":3,"toHeroId":20,"value":50},{"type":1000,"fromHeroId":121,"toHeroId":54,"value":50},{"type":1000,"fromHeroId":20,"toHeroId":126,"value":50},{"type":1000,"fromHeroId":54,"toHeroId":121,"value":50},{"type":12,"fromHeroId":{},"toHeroId":{},"value":0},{"type":5,"fromHeroId":63,"toHeroId":{},"value":347},{"type":12,"fromHeroId":{},"toHeroId":{},"value":0},{"type":10,"fromHeroId":{},"toHeroId":{},"value":0},{"type":10,"fromHeroId":{},"toHeroId":{},"value":0},{"type":12,"fromHeroId":{},"toHeroId":{},"value":0},{"type":12,"fromHeroId":{},"toHeroId":{},"value":0},{"type":11,"fromHeroId":{},"toHeroId":{},"value":0},{"type":11,"fromHeroId":{},"toHeroId":{},"value":0},{"type":1000,"fromHeroId":3,"toHeroId":51,"value":50},{"type":114,"fromHeroId":121,"toHeroId":{},"value":4},{"type":12,"fromHeroId":{},"toHeroId":{},"value":0},{"type":12,"fromHeroId":{},"toHeroId":{},"value":0},{"type":12,"fromHeroId":{},"toHeroId":{},"value":0},{"type":1000,"fromHeroId":126,"toHeroId":51,"value":50},{"type":1000,"fromHeroId":3,"toHeroId":51,"value":50},{"type":1000,"fromHeroId":96,"toHeroId":51,"value":50},{"type":1000,"fromHeroId":121,"toHeroId":51,"value":50},{"type":15,"fromHeroId":20,"toHeroId":{},"value":0},{"type":15,"fromHeroId":10,"toHeroId":{},"value":0},{"type":91,"fromHeroId":10,"toHeroId":{},"value":0},{"type":15,"fromHeroId":54,"toHeroId":{},"value":0},{"type":15,"fromHeroId":126,"toHeroId":{},"value":0},{"type":15,"fromHeroId":17,"toHeroId":{},"value":0},{"type":15,"fromHeroId":51,"toHeroId":{},"value":0},{"type":15,"fromHeroId":63,"toHeroId":{},"value":0},{"type":15,"fromHeroId":96,"toHeroId":{},"value":0},{"type":15,"fromHeroId":121,"toHeroId":{},"value":0},{"type":15,"fromHeroId":3,"toHeroId":{},"value":0}],"players":[{"steamAccountId":171262902,"heroId":10,"dotaPlus":{"level":30}},{"steamAccountId":56351509,"heroId":96,"dotaPlus":{"level":17}},{"steamAccountId":106573901,"heroId":126,"dotaPlus":{"level":26}},{"steamAccountId":127565532,"heroId":3,"dotaPlus":{"level":30}},{"steamAccountId":196878136,"heroId":121,"dotaPlus":{"level":17}},{"steamAccountId":331855530,"heroId":54,"dotaPlus":{"level":11}},{"steamAccountId":132851371,"heroId":20,"dotaPlus":{}},{"steamAccountId":136829091,"heroId":63,"dotaPlus":{"level":12}},{"steamAccountId":164199202,"heroId":51,"dotaPlus":{}},{"steamAccountId":94054712,"heroId":17,"dotaPlus":{"level":17}}]}}
