{"match":{"startDateTime":1720271463,"chatEvents":[{"type":1000,"fromHeroId":33,"toHeroId":35,"value":50},{"type":1000,"fromHeroId":136,"toHeroId":120,"value":50},{"type":1000,"fromHeroId":120,"toHeroId":81,"value":50},{"type":5,"fromHeroId":123,"toHeroId":{},"value":341},{"type":12,"fromHeroId":{},"toHeroId":{},"value":0},{"type":1000,"fromHeroId":33,"toHeroId":35,"value":50},{"type":12,"fromHeroId":{},"toHeroId":{},"value":0},{"type":12,"fromHeroId":{},"toHeroId":{},"value":0},{"type":12,"fromHeroId":{},"toHeroId":{},"value":0},{"type":12,"fromHeroId":{},"toHeroId":{},"value":0},{"type":12,"fromHeroId":{},"toHeroId":{},"value":0},{"type":11,"fromHeroId":{},"toHeroId":{},"value":0},{"type":12,"fromHeroId":{},"toHeroId":{},"value":0},{"type":11,"fromHeroId":{},"toHeroId":{},"value":0},{"type":91,"fromHeroId":123,"toHeroId":{},"value":0},{"type":12,"fromHeroId":{},"toHeroId":{},"value":0},{"type":12,"fromHeroId":{},"toHeroId":{},"value":0},{"type":12,"fromHeroId":{},"toHeroId":{},"value":0},{"type":12,"fromHeroId":{},"toHeroId":{},"value":0},{"type":91,"fromHeroId":78,"toHeroId":{},"value":0},{"type":11,"fromHeroId":{},"toHeroId":{},"value":0},{"type":12,"fromHeroId":{},"toHeroId":{},"value":0},{"type":1000,"fromHeroId":78,"toHeroId":35,"value":50},{"type":15,"fromHeroId":120,"toHeroId":{},"value":0},{"type":15,"fromHeroId":136,"toHeroId":{},"value":0},{"type":15,"fromHeroId":78,"toHeroId":{},"value":0},{"type":15,"fromHeroId":35,"toHeroId":{},"value":0},{"type":15,"fromHeroId":103,"toHeroId":{},"value":0},{"type":15,"fromHeroId":114,"toHeroId":{},"value":0},{"type":15,"fromHeroId":33,"toHeroId":{},"value":0},{"type":15,"fromHeroId":81,"toHeroId":{},"value":0},{"type":15,"fromHeroId":123,"toHeroId":{},"value":0},{"type":11,"fromHeroId":{},"toHeroId":{},"value":0},{"type":15,"fromHeroId":110,"toHeroId":{},"value":0}],"players":[{"steamAccountId":100471531,"heroId":78,"dotaPlus":{}},{"steamAccountId":375507918,"heroId":35,"dotaPlus":{"level":15}},{"steamAccountId":101259972,"heroId":103,"dotaPlus":{}},{"steamAccountId":210053851,"heroId":120,"dotaPlus":{"level":17}},{"steamAccountId":193815691,"heroId":123,"dotaPlus":{"level":20}},{"steamAccountId":81306398,"heroId":110,"dotaPlus":{"level":19}},{"steamAccountId":131303632,"heroId":114,"dotaPlus":{"level":19}},{"steamAccountId":164685175,"heroId":81,"dotaPlus":{"level":12}},{"steamAccountId":157989498,"heroId":136,"dotaPlus":{}},{"steamAccountId":138880576,"heroId":33,"dotaPlus":{"level":22}}]}}
