{"match":{"startDateTime":1720724884,"chatEvents":[{"type":1000,"fromHeroId":33,"toHeroId":86,"value":50},{"type":1000,"fromHeroId":86,"toHeroId":33,"value":50},{"type":1000,"fromHeroId":49,"toHeroId":78,"value":50},{"type":5,"fromHeroId":11,"toHeroId":{},"value":356},{"type":114,"fromHeroId":11,"toHeroId":{},"value":7},{"type":12,"fromHeroId":{},"toHeroId":{},"value":0},{"type":12,"fromHeroId":{},"toHeroId":{},"value":0},{"type":114,"fromHeroId":86,"toHeroId":{},"value":5},{"type":1000,"fromHeroId":49,"toHeroId":78,"value":50},{"type":12,"fromHeroId":{},"toHeroId":{},"value":0},{"type":114,"fromHeroId":128,"toHeroId":{},"value":6},{"type":114,"fromHeroId":10,"toHeroId":{},"value":2},{"type":117,"fromHeroId":136,"toHeroId":{},"value":2},{"type":117,"fromHeroId":10,"toHeroId":{},"value":3},{"type":12,"fromHeroId":{},"toHeroId":{},"value":0},{"type":10,"fromHeroId":{},"toHeroId":{},"value":0},{"type":11,"fromHeroId":{},"toHeroId":{},"value":0},{"type":12,"fromHeroId":{},"toHeroId":{},"value":0},{"type":1000,"fromHeroId":136,"toHeroId":10,"value":50},{"type":11,"fromHeroId":{},"toHeroId":{},"value":0},{"type":114,"fromHeroId":78,"toHeroId":{},"value":4},{"type":117,"fromHeroId":22,"toHeroId":{},"value":2},{"type":1000,"fromHeroId":49,"toHeroId":78,"value":50},{"type":1000,"fromHeroId":128,"toHeroId":33,"value":50},{"type":1000,"fromHeroId":22,"toHeroId":33,"value":50},{"type":12,"fromHeroId":{},"toHeroId":{},"value":0},{"type":12,"fromHeroId":{},"toHeroId":{},"value":0},{"type":15,"fromHeroId":33,"toHeroId":{},"value":0},{"type":15,"fromHeroId":11,"toHeroId":{},"value":0},{"type":15,"fromHeroId":136,"toHeroId":{},"value":0},{"type":15,"fromHeroId":78,"toHeroId":{},"value":0},{"type":15,"fromHeroId":128,"toHeroId":{},"value":0},{"type":15,"fromHeroId":63,"toHeroId":{},"value":0},{"type":15,"fromHeroId":10,"toHeroId":{},"value":0},{"type":15,"fromHeroId":22,"toHeroId":{},"value":0},{"type":15,"fromHeroId":49,"toHeroId":{},"value":0},{"type":15,"fromHeroId":86,"toHeroId":{},"value":0},{"type":11,"fromHeroId":{},"toHeroId":{},"value":0},{"type":11,"fromHeroId":{},"toHeroId":{},"value":0}],"players":[{"steamAccountId":331855530,"heroId":49,"dotaPlus":{},"playbackData":{"runeEvents":[{"time":0,"rune":"BOUNTY","action":"PICKUP"},{"time":540,"rune":"BOUNTY","action":"PICKUP"},{"time":887,"rune":"WISDOM","action":"PICKUP"},{"time":1404,"rune":"BOUNTY","action":"PICKUP"},{"time":1493,"rune":"BOUNTY","action":"PICKUP"}],"killEvents":[{"time":974,"isSmoke":false,"isRuneEffected":false},{"time":1273,"isSmoke":false,"isRuneEffected":false},{"time":1415,"isSmoke":true,"isRuneEffected":false},{"time":1744,"isSmoke":false,"isRuneEffected":false},{"time":1856,"isSmoke":false,"isRuneEffected":false},{"time":2075,"isSmoke":false,"isRuneEffected":false},{"time":2080,"isSmoke":false,"isRuneEffected":false},{"time":2125,"isSmoke":false,"isRuneEffected":false}]}},{"steamAccountId":132851371,"heroId":33,"dotaPlus":{"level":11},"playbackData":{"runeEvents":[{"time":902,"rune":"BOUNTY","action":"PICKUP"},{"time":1125,"rune":"BOUNTY","action":"PICKUP"}],"killEvents":[{"time":1086,"isSmoke":false,"isRuneEffected":false},{"time":1439,"isSmoke":true,"isRuneEffected":false},{"time":1642,"isSmoke":true,"isRuneEffected":false}]}},{"steamAccountId":136829091,"heroId":128,"dotaPlus":{"level":17},"playbackData":{"runeEvents":[{"time":0,"rune":"BOUNTY","action":"PICKUP"},{"time":218,"rune":"BOUNTY","action":"PICKUP"},{"time":240,"rune":"WATER","action":"PICKUP"},{"time":425,"rune":"WISDOM","action":"PICKUP"},{"time":1628,"rune":"BOUNTY","action":"PICKUP"}],"killEvents":[{"time":311,"isSmoke":false,"isRuneEffected":false},{"time":1070,"isSmoke":false,"isRuneEffected":false}]}},{"steamAccountId":164199202,"heroId":136,"dotaPlus":{"level":13},"playbackData":{"runeEvents":[{"time":698,"rune":"BOUNTY","action":"PICKUP"},{"time":942,"rune":"BOUNTY","action":"PICKUP"},{"time":1705,"rune":"WISDOM","action":"PICKUP"}],"killEvents":[{"time":786,"isSmoke":false,"isRuneEffected":false},{"time":949,"isSmoke":true,"isRuneEffected":false},{"time":1526,"isSmoke":false,"isRuneEffected":false}]}},{"steamAccountId":94054712,"heroId":22,"dotaPlus":{"level":29},"playbackData":{"runeEvents":[{"time":153,"rune":"WATER","action":"BOTTLE"},{"time":190,"rune":"WATER","action":"PICKUP"},{"time":240,"rune":"WATER","action":"BOTTLE"},{"time":276,"rune":"WATER","action":"PICKUP"},{"time":285,"rune":"BOUNTY","action":"BOTTLE"},{"time":286,"rune":"BOUNTY","action":"PICKUP"},{"time":365,"rune":"REGEN","action":"BOTTLE"},{"time":383,"rune":"REGEN","action":"PICKUP"},{"time":488,"rune":"INVISIBILITY","action":"BOTTLE"},{"time":509,"rune":"INVISIBILITY","action":"PICKUP"},{"time":604,"rune":"HASTE","action":"BOTTLE"},{"time":634,"rune":"HASTE","action":"PICKUP"},{"time":730,"rune":"BOUNTY","action":"BOTTLE"},{"time":769,"rune":"BOUNTY","action":"PICKUP"},{"time":796,"rune":"BOUNTY","action":"BOTTLE"},{"time":802,"rune":"BOUNTY","action":"PICKUP"},{"time":849,"rune":"ILLUSION","action":"BOTTLE"},{"time":900,"rune":"ILLUSION","action":"PICKUP"},{"time":977,"rune":"SHIELD","action":"BOTTLE"},{"time":1011,"rune":"SHIELD","action":"PICKUP"},{"time":1347,"rune":"DOUBLE_DAMAGE","action":"BOTTLE"},{"time":1405,"rune":"DOUBLE_DAMAGE","action":"PICKUP"},{"time":1457,"rune":"INVISIBILITY","action":"BOTTLE"},{"time":1466,"rune":"INVISIBILITY","action":"PICKUP"},{"time":2056,"rune":"DOUBLE_DAMAGE","action":"BOTTLE"},{"time":2060,"rune":"DOUBLE_DAMAGE","action":"PICKUP"}],"killEvents":[{"time":91,"isSmoke":false,"isRuneEffected":false},{"time":271,"isSmoke":false,"isRuneEffected":false},{"time":375,"isSmoke":false,"isRuneEffected":false},{"time":391,"isSmoke":false,"isRuneEffected":true},{"time":640,"isSmoke":false,"isRuneEffected":true},{"time":1078,"isSmoke":false,"isRuneEffected":false},{"time":1137,"isSmoke":false,"isRuneEffected":false},{"time":1445,"isSmoke":false,"isRuneEffected":true},{"time":1640,"isSmoke":true,"isRuneEffected":false},{"time":2042,"isSmoke":false,"isRuneEffected":false},{"time":2077,"isSmoke":false,"isRuneEffected":true},{"time":2081,"isSmoke":false,"isRuneEffected":true},{"time":2126,"isSmoke":false,"isRuneEffected":false}]}},{"steamAccountId":54580962,"heroId":86,"dotaPlus":{"level":29},"playbackData":{"runeEvents":[{"time":0,"rune":"BOUNTY","action":"PICKUP"},{"time":444,"rune":"BOUNTY","action":"PICKUP"}],"killEvents":[]}},{"steamAccountId":86698277,"heroId":78,"dotaPlus":{"level":22},"playbackData":{"runeEvents":[{"time":1268,"rune":"WISDOM","action":"PICKUP"},{"time":1687,"rune":"WISDOM","action":"PICKUP"}],"killEvents":[{"time":285,"isSmoke":false,"isRuneEffected":false},{"time":1068,"isSmoke":true,"isRuneEffected":false}]}},{"steamAccountId":201358612,"heroId":11,"dotaPlus":{},"playbackData":{"runeEvents":[{"time":1165,"rune":"DOUBLE_DAMAGE","action":"BOTTLE"},{"time":1255,"rune":"DOUBLE_DAMAGE","action":"PICKUP"},{"time":1263,"rune":"BOUNTY","action":"BOTTLE"},{"time":1264,"rune":"BOUNTY","action":"PICKUP"},{"time":1443,"rune":"BOUNTY","action":"PICKUP"},{"time":1579,"rune":"HASTE","action":"BOTTLE"},{"time":1626,"rune":"HASTE","action":"PICKUP"},{"time":1804,"rune":"SHIELD","action":"BOTTLE"},{"time":1814,"rune":"BOUNTY","action":"PICKUP"},{"time":1894,"rune":"SHIELD","action":"PICKUP"},{"time":2048,"rune":"BOUNTY","action":"PICKUP"},{"time":2048,"rune":"BOUNTY","action":"PICKUP"}],"killEvents":[{"time":1278,"isSmoke":false,"isRuneEffected":true},{"time":1747,"isSmoke":false,"isRuneEffected":false}]}},{"steamAccountId":77490514,"heroId":10,"dotaPlus":{},"playbackData":{"runeEvents":[{"time":434,"rune":"WISDOM","action":"PICKUP"},{"time":651,"rune":"BOUNTY","action":"PICKUP"},{"time":866,"rune":"BOUNTY","action":"PICKUP"},{"time":887,"rune":"WISDOM","action":"PICKUP"},{"time":1023,"rune":"BOUNTY","action":"PICKUP"},{"time":1175,"rune":"BOUNTY","action":"PICKUP"},{"time":1260,"rune":"BOUNTY","action":"PICKUP"},{"time":1260,"rune":"WISDOM","action":"PICKUP"},{"time":1691,"rune":"ARCANE","action":"PICKUP"},{"time":1968,"rune":"BOUNTY","action":"PICKUP"}],"killEvents":[{"time":508,"isSmoke":false,"isRuneEffected":false},{"time":736,"isSmoke":true,"isRuneEffected":false},{"time":1142,"isSmoke":true,"isRuneEffected":false},{"time":1151,"isSmoke":true,"isRuneEffected":false}]}},{"steamAccountId":152962063,"heroId":63,"dotaPlus":{"level":11},"playbackData":{"runeEvents":[{"time":0,"rune":"BOUNTY","action":"PICKUP"},{"time":1793,"rune":"BOUNTY","action":"PICKUP"}],"killEvents":[{"time":283,"isSmoke":false,"isRuneEffected":false},{"time":1153,"isSmoke":false,"isRuneEffected":false},{"time":1643,"isSmoke":false,"isRuneEffected":false},{"time":1765,"isSmoke":false,"isRuneEffected":false}]}}]}}
