{"match":{"startDateTime":1720960200,"chatEvents":[{"type":1000,"fromHeroId":55,"toHeroId":13,"value":50},{"type":10,"fromHeroId":{},"toHeroId":{},"value":0},{"type":5,"fromHeroId":129,"toHeroId":{},"value":356},{"type":11,"fromHeroId":{},"toHeroId":{},"value":0},{"type":12,"fromHeroId":{},"toHeroId":{},"value":0},{"type":12,"fromHeroId":{},"toHeroId":{},"value":0},{"type":11,"fromHeroId":{},"toHeroId":{},"value":0},{"type":12,"fromHeroId":{},"toHeroId":{},"value":0},{"type":12,"fromHeroId":{},"toHeroId":{},"value":0},{"type":12,"fromHeroId":{},"toHeroId":{},"value":0},{"type":11,"fromHeroId":{},"toHeroId":{},"value":0},{"type":11,"fromHeroId":{},"toHeroId":{},"value":0},{"type":117,"fromHeroId":103,"toHeroId":{},"value":3},{"type":12,"fromHeroId":{},"toHeroId":{},"value":0},{"type":117,"fromHeroId":110,"toHeroId":{},"value":2},{"type":10,"fromHeroId":{},"toHeroId":{},"value":0},{"type":12,"fromHeroId":{},"toHeroId":{},"value":0},{"type":12,"fromHeroId":{},"toHeroId":{},"value":0},{"type":11,"fromHeroId":{},"toHeroId":{},"value":0},{"type":1000,"fromHeroId":129,"toHeroId":71,"value":50},{"type":12,"fromHeroId":{},"toHeroId":{},"value":0},{"type":117,"fromHeroId":71,"toHeroId":{},"value":2},{"type":12,"fromHeroId":{},"toHeroId":{},"value":0},{"type":12,"fromHeroId":{},"toHeroId":{},"value":0},{"type":119,"fromHeroId":110,"toHeroId":{},"value":0},{"type":12,"fromHeroId":{},"toHeroId":{},"value":0},{"type":12,"fromHeroId":{},"toHeroId":{},"value":0},{"type":117,"fromHeroId":129,"toHeroId":{},"value":3},{"type":119,"fromHeroId":55,"toHeroId":{},"value":0},{"type":91,"fromHeroId":55,"toHeroId":{},"value":0},{"type":119,"fromHeroId":55,"toHeroId":{},"value":0},{"type":117,"fromHeroId":16,"toHeroId":{},"value":2},{"type":28,"fromHeroId":{},"toHeroId":{},"value":0},{"type":91,"fromHeroId":16,"toHeroId":{},"value":0},{"type":15,"fromHeroId":11,"toHeroId":{},"value":0},{"type":15,"fromHeroId":21,"toHeroId":{},"value":0},{"type":15,"fromHeroId":16,"toHeroId":{},"value":0},{"type":15,"fromHeroId":13,"toHeroId":{},"value":0},{"type":15,"fromHeroId":103,"toHeroId":{},"value":0},{"type":15,"fromHeroId":71,"toHeroId":{},"value":0},{"type":15,"fromHeroId":129,"toHeroId":{},"value":0},{"type":15,"fromHeroId":55,"toHeroId":{},"value":0},{"type":15,"fromHeroId":88,"toHeroId":{},"value":0},{"type":15,"fromHeroId":110,"toHeroId":{},"value":0}],"players":[{"steamAccountId":154715080,"heroId":16,"dotaPlus":{}},{"steamAccountId":155494381,"heroId":71,"dotaPlus":{"level":11}},{"steamAccountId":148526973,"heroId":110,"dotaPlus":{"level":18}},{"steamAccountId":152545459,"heroId":55,"dotaPlus":{"level":13}},{"steamAccountId":355168766,"heroId":21,"dotaPlus":{"level":18}},{"steamAccountId":321580662,"heroId":11,"dotaPlus":{"level":16}},{"steamAccountId":113331514,"heroId":103,"dotaPlus":{}},{"steamAccountId":106305042,"heroId":13,"dotaPlus":{"level":20}},{"steamAccountId":256156323,"heroId":88,"dotaPlus":{}},{"steamAccountId":302214028,"heroId":129,"dotaPlus":{"level":23}}]}}
