{"match":{"startDateTime":1721143200,"chatEvents":[{"type":1000,"fromHeroId":120,"toHeroId":20,"value":50},{"type":1000,"fromHeroId":20,"toHeroId":120,"value":50},{"type":11,"fromHeroId":{},"toHeroId":{},"value":0},{"type":11,"fromHeroId":{},"toHeroId":{},"value":0},{"type":12,"fromHeroId":{},"toHeroId":{},"value":0},{"type":5,"fromHeroId":109,"toHeroId":{},"value":388},{"type":12,"fromHeroId":{},"toHeroId":{},"value":0},{"type":11,"fromHeroId":{},"toHeroId":{},"value":0},{"type":10,"fromHeroId":{},"toHeroId":{},"value":0},{"type":12,"fromHeroId":{},"toHeroId":{},"value":0},{"type":34,"fromHeroId":64,"toHeroId":{},"value":0},{"type":36,"fromHeroId":64,"toHeroId":{},"value":0},{"type":11,"fromHeroId":{},"toHeroId":{},"value":0},{"type":10,"fromHeroId":{},"toHeroId":{},"value":0},{"type":117,"fromHeroId":110,"toHeroId":{},"value":2},{"type":12,"fromHeroId":{},"toHeroId":{},"value":0},{"type":11,"fromHeroId":{},"toHeroId":{},"value":0},{"type":12,"fromHeroId":{},"toHeroId":{},"value":0},{"type":117,"fromHeroId":64,"toHeroId":{},"value":3},{"type":1000,"fromHeroId":120,"toHeroId":109,"value":50},{"type":12,"fromHeroId":{},"toHeroId":{},"value":0},{"type":1000,"fromHeroId":120,"toHeroId":109,"value":50},{"type":1000,"fromHeroId":98,"toHeroId":109,"value":50},{"type":12,"fromHeroId":{},"toHeroId":{},"value":0},{"type":12,"fromHeroId":{},"toHeroId":{},"value":0},{"type":117,"fromHeroId":86,"toHeroId":{},"value":2},{"type":117,"fromHeroId":58,"toHeroId":{},"value":3},{"type":91,"fromHeroId":86,"toHeroId":{},"value":0},{"type":117,"fromHeroId":20,"toHeroId":{},"value":2},{"type":117,"fromHeroId":98,"toHeroId":{},"value":3},{"type":12,"fromHeroId":{},"toHeroId":{},"value":0},{"type":91,"fromHeroId":20,"toHeroId":{},"value":0},{"type":1000,"fromHeroId":98,"toHeroId":109,"value":50},{"type":15,"fromHeroId":109,"toHeroId":{},"value":0},{"type":15,"fromHeroId":20,"toHeroId":{},"value":0},{"type":15,"fromHeroId":120,"toHeroId":{},"value":0},{"type":15,"fromHeroId":110,"toHeroId":{},"value":0},{"type":15,"fromHeroId":96,"toHeroId":{},"value":0},{"type":15,"fromHeroId":86,"toHeroId":{},"value":0},{"type":15,"fromHeroId":98,"toHeroId":{},"value":0},{"type":15,"fromHeroId":64,"toHeroId":{},"value":0},{"type":15,"fromHeroId":18,"toHeroId":{},"value":0},{"type":15,"fromHeroId":58,"toHeroId":{},"value":0}],"players":[{"steamAccountId":898754153,"heroId":109,"dotaPlus":{"level":28},"playbackData":{"runeEvents":[{"time":1113,"rune":"BOUNTY","action":"PICKUP"},{"time":1113,"rune":"BOUNTY","action":"PICKUP"},{"time":1928,"rune":"ILLUSION","action":"PICKUP"},{"time":2329,"rune":"ILLUSION","action":"PICKUP"}],"killEvents":[{"time":382,"isSmoke":false,"isRuneEffected":false},{"time":716,"isSmoke":false,"isRuneEffected":false}]}},{"steamAccountId":143693439,"heroId":110,"dotaPlus":{"level":16},"playbackData":{"runeEvents":[{"time":342,"rune":"BOUNTY","action":"PICKUP"},{"time":520,"rune":"BOUNTY","action":"PICKUP"},{"time":520,"rune":"BOUNTY","action":"PICKUP"},{"time":542,"rune":"BOUNTY","action":"PICKUP"},{"time":1266,"rune":"BOUNTY","action":"PICKUP"},{"time":1446,"rune":"BOUNTY","action":"PICKUP"},{"time":1851,"rune":"BOUNTY","action":"PICKUP"},{"time":2213,"rune":"BOUNTY","action":"PICKUP"}],"killEvents":[{"time":1129,"isSmoke":false,"isRuneEffected":false}]}},{"steamAccountId":137129583,"heroId":20,"dotaPlus":{},"playbackData":{"runeEvents":[{"time":138,"rune":"WATER","action":"BOTTLE"},{"time":189,"rune":"WATER","action":"PICKUP"},{"time":254,"rune":"WATER","action":"BOTTLE"},{"time":254,"rune":"WATER","action":"PICKUP"},{"time":369,"rune":"BOUNTY","action":"BOTTLE"},{"time":369,"rune":"BOUNTY","action":"PICKUP"},{"time":721,"rune":"SHIELD","action":"BOTTLE"},{"time":744,"rune":"SHIELD","action":"PICKUP"},{"time":1443,"rune":"SHIELD","action":"BOTTLE"},{"time":1475,"rune":"SHIELD","action":"PICKUP"}],"killEvents":[{"time":2164,"isSmoke":true,"isRuneEffected":false}]}},{"steamAccountId":157475523,"heroId":86,"dotaPlus":{"level":21},"playbackData":{"runeEvents":[{"time":0,"rune":"BOUNTY","action":"PICKUP"},{"time":425,"rune":"WISDOM","action":"PICKUP"},{"time":840,"rune":"WISDOM","action":"PICKUP"},{"time":1260,"rune":"WISDOM","action":"PICKUP"},{"time":1682,"rune":"WISDOM","action":"PICKUP"},{"time":2105,"rune":"WISDOM","action":"PICKUP"},{"time":2521,"rune":"WISDOM","action":"PICKUP"}],"killEvents":[]}},{"steamAccountId":129958758,"heroId":96,"dotaPlus":{"level":13},"playbackData":{"runeEvents":[{"time":0,"rune":"BOUNTY","action":"PICKUP"}],"killEvents":[]}},{"steamAccountId":10366616,"heroId":58,"dotaPlus":{"level":22},"playbackData":{"runeEvents":[{"time":490,"rune":"BOUNTY","action":"PICKUP"},{"time":583,"rune":"BOUNTY","action":"PICKUP"},{"time":621,"rune":"BOUNTY","action":"PICKUP"},{"time":877,"rune":"BOUNTY","action":"PICKUP"},{"time":1153,"rune":"BOUNTY","action":"PICKUP"},{"time":1267,"rune":"BOUNTY","action":"PICKUP"},{"time":1824,"rune":"BOUNTY","action":"PICKUP"},{"time":2166,"rune":"INVISIBILITY","action":"PICKUP"},{"time":2700,"rune":"BOUNTY","action":"PICKUP"}],"killEvents":[]}},{"steamAccountId":100058342,"heroId":18,"dotaPlus":{"level":21},"playbackData":{"runeEvents":[{"time":720,"rune":"BOUNTY","action":"PICKUP"},{"time":1624,"rune":"BOUNTY","action":"PICKUP"},{"time":1680,"rune":"WISDOM","action":"PICKUP"},{"time":1700,"rune":"DOUBLE_DAMAGE","action":"BOTTLE"},{"time":1767,"rune":"DOUBLE_DAMAGE","action":"PICKUP"},{"time":1982,"rune":"BOUNTY","action":"PICKUP"},{"time":2170,"rune":"BOUNTY","action":"PICKUP"},{"time":2170,"rune":"BOUNTY","action":"PICKUP"},{"time":2765,"rune":"DOUBLE_DAMAGE","action":"BOTTLE"},{"time":2856,"rune":"DOUBLE_DAMAGE","action":"PICKUP"}],"killEvents":[{"time":1479,"isSmoke":true,"isRuneEffected":false},{"time":2276,"isSmoke":true,"isRuneEffected":false},{"time":2291,"isSmoke":true,"isRuneEffected":false},{"time":2612,"isSmoke":true,"isRuneEffected":false},{"time":2883,"isSmoke":true,"isRuneEffected":true}]}},{"steamAccountId":898455820,"heroId":120,"dotaPlus":{"level":30},"playbackData":{"runeEvents":[{"time":142,"rune":"WATER","action":"BOTTLE"},{"time":232,"rune":"WATER","action":"PICKUP"},{"time":253,"rune":"WATER","action":"BOTTLE"},{"time":287,"rune":"WATER","action":"PICKUP"},{"time":363,"rune":"DOUBLE_DAMAGE","action":"BOTTLE"},{"time":396,"rune":"DOUBLE_DAMAGE","action":"PICKUP"},{"time":497,"rune":"ILLUSION","action":"BOTTLE"},{"time":587,"rune":"ILLUSION","action":"PICKUP"},{"time":610,"rune":"INVISIBILITY","action":"BOTTLE"},{"time":658,"rune":"INVISIBILITY","action":"PICKUP"},{"time":841,"rune":"REGEN","action":"BOTTLE"},{"time":876,"rune":"REGEN","action":"PICKUP"},{"time":903,"rune":"BOUNTY","action":"BOTTLE"},{"time":904,"rune":"BOUNTY","action":"PICKUP"},{"time":965,"rune":"HASTE","action":"BOTTLE"},{"time":973,"rune":"HASTE","action":"PICKUP"},{"time":1087,"rune":"ARCANE","action":"BOTTLE"},{"time":1105,"rune":"ARCANE","action":"PICKUP"},{"time":1252,"rune":"REGEN","action":"BOTTLE"},{"time":1282,"rune":"REGEN","action":"PICKUP"},{"time":1323,"rune":"HASTE","action":"BOTTLE"},{"time":1414,"rune":"HASTE","action":"PICKUP"},{"time":1566,"rune":"INVISIBILITY","action":"BOTTLE"},{"time":1633,"rune":"INVISIBILITY","action":"PICKUP"},{"time":1815,"rune":"ARCANE","action":"BOTTLE"},{"time":1905,"rune":"ARCANE","action":"PICKUP"},{"time":2111,"rune":"SHIELD","action":"PICKUP"},{"time":2403,"rune":"HASTE","action":"BOTTLE"},{"time":2494,"rune":"HASTE","action":"PICKUP"},{"time":2526,"rune":"ARCANE","action":"BOTTLE"},{"time":2556,"rune":"WISDOM","action":"PICKUP"},{"time":2600,"rune":"ARCANE","action":"PICKUP"},{"time":2658,"rune":"REGEN","action":"PICKUP"},{"time":2736,"rune":"BOUNTY","action":"PICKUP"}],"killEvents":[{"time":985,"isSmoke":false,"isRuneEffected":true},{"time":1201,"isSmoke":false,"isRuneEffected":false},{"time":1800,"isSmoke":false,"isRuneEffected":false}]}},{"steamAccountId":183719386,"heroId":98,"dotaPlus":{"level":30},"playbackData":{"runeEvents":[{"time":0,"rune":"BOUNTY","action":"PICKUP"},{"time":1587,"rune":"BOUNTY","action":"PICKUP"},{"time":1663,"rune":"BOUNTY","action":"PICKUP"}],"killEvents":[{"time":328,"isSmoke":false,"isRuneEffected":false},{"time":379,"isSmoke":false,"isRuneEffected":false},{"time":470,"isSmoke":false,"isRuneEffected":false},{"time":1198,"isSmoke":false,"isRuneEffected":false},{"time":1356,"isSmoke":true,"isRuneEffected":false},{"time":2014,"isSmoke":false,"isRuneEffected":false},{"time":2029,"isSmoke":false,"isRuneEffected":false},{"time":2283,"isSmoke":true,"isRuneEffected":false},{"time":2894,"isSmoke":false,"isRuneEffected":false},{"time":2908,"isSmoke":false,"isRuneEffected":false},{"time":2928,"isSmoke":false,"isRuneEffected":false},{"time":2931,"isSmoke":false,"isRuneEffected":false}]}},{"steamAccountId":25907144,"heroId":64,"dotaPlus":{},"playbackData":{"runeEvents":[{"time":7,"rune":"BOUNTY","action":"PICKUP"},{"time":510,"rune":"WISDOM","action":"PICKUP"},{"time":730,"rune":"BOUNTY","action":"PICKUP"},{"time":733,"rune":"BOUNTY","action":"PICKUP"},{"time":864,"rune":"WISDOM","action":"PICKUP"},{"time":1124,"rune":"BOUNTY","action":"PICKUP"},{"time":1243,"rune":"BOUNTY","action":"PICKUP"},{"time":1266,"rune":"WISDOM","action":"PICKUP"},{"time":1416,"rune":"BOUNTY","action":"PICKUP"},{"time":2116,"rune":"WISDOM","action":"PICKUP"},{"time":2357,"rune":"BOUNTY","action":"PICKUP"},{"time":2403,"rune":"BOUNTY","action":"PICKUP"},{"time":2536,"rune":"BOUNTY","action":"PICKUP"},{"time":2684,"rune":"BOUNTY","action":"PICKUP"}],"killEvents":[{"time":984,"isSmoke":true,"isRuneEffected":false},{"time":2029,"isSmoke":false,"isRuneEffected":false}]}}]}}
