{"match":{"startDateTime":1722168448,"chatEvents":[{"type":34,"fromHeroId":17,"toHeroId":{},"value":0},{"type":15,"fromHeroId":17,"toHeroId":{},"value":0},{"type":15,"fromHeroId":63,"toHeroId":{},"value":0},{"type":15,"fromHeroId":78,"toHeroId":{},"value":0},{"type":19,"fromHeroId":17,"toHeroId":{},"value":0},{"type":19,"fromHeroId":63,"toHeroId":{},"value":0},{"type":19,"fromHeroId":78,"toHeroId":{},"value":0},{"type":36,"fromHeroId":88,"toHeroId":{},"value":0},{"type":5,"fromHeroId":63,"toHeroId":{},"value":350},{"type":10,"fromHeroId":{},"toHeroId":{},"value":0},{"type":11,"fromHeroId":{},"toHeroId":{},"value":0},{"type":12,"fromHeroId":{},"toHeroId":{},"value":0},{"type":12,"fromHeroId":{},"toHeroId":{},"value":0},{"type":114,"fromHeroId":66,"toHeroId":{},"value":3},{"type":12,"fromHeroId":{},"toHeroId":{},"value":0},{"type":114,"fromHeroId":66,"toHeroId":{},"value":9},{"type":117,"fromHeroId":63,"toHeroId":{},"value":2},{"type":117,"fromHeroId":66,"toHeroId":{},"value":3},{"type":12,"fromHeroId":{},"toHeroId":{},"value":0},{"type":10,"fromHeroId":{},"toHeroId":{},"value":0},{"type":12,"fromHeroId":{},"toHeroId":{},"value":0},{"type":11,"fromHeroId":{},"toHeroId":{},"value":0},{"type":12,"fromHeroId":{},"toHeroId":{},"value":0},{"type":12,"fromHeroId":{},"toHeroId":{},"value":0},{"type":12,"fromHeroId":{},"toHeroId":{},"value":0},{"type":117,"fromHeroId":86,"toHeroId":{},"value":3},{"type":117,"fromHeroId":54,"toHeroId":{},"value":2},{"type":12,"fromHeroId":{},"toHeroId":{},"value":0},{"type":12,"fromHeroId":{},"toHeroId":{},"value":0},{"type":117,"fromHeroId":17,"toHeroId":{},"value":2},{"type":117,"fromHeroId":49,"toHeroId":{},"value":3},{"type":119,"fromHeroId":110,"toHeroId":{},"value":0},{"type":12,"fromHeroId":{},"toHeroId":{},"value":0},{"type":28,"fromHeroId":{},"toHeroId":{},"value":0},{"type":91,"fromHeroId":66,"toHeroId":{},"value":0},{"type":91,"fromHeroId":88,"toHeroId":{},"value":0},{"type":15,"fromHeroId":86,"toHeroId":{},"value":0},{"type":15,"fromHeroId":78,"toHeroId":{},"value":0},{"type":15,"fromHeroId":54,"toHeroId":{},"value":0},{"type":15,"fromHeroId":88,"toHeroId":{},"value":0},{"type":15,"fromHeroId":16,"toHeroId":{},"value":0},{"type":15,"fromHeroId":66,"toHeroId":{},"value":0},{"type":15,"fromHeroId":63,"toHeroId":{},"value":0},{"type":15,"fromHeroId":17,"toHeroId":{},"value":0},{"type":15,"fromHeroId":49,"toHeroId":{},"value":0},{"type":15,"fromHeroId":110,"toHeroId":{},"value":0}],"players":[{"steamAccountId":111620041,"heroId":17,"dotaPlus":{"level":13}},{"steamAccountId":156328257,"heroId":78,"dotaPlus":{"level":20}},{"steamAccountId":101356886,"heroId":110,"dotaPlus":{}},{"steamAccountId":181267255,"heroId":63,"dotaPlus":{}},{"steamAccountId":206642367,"heroId":54,"dotaPlus":{"level":30}},{"steamAccountId":898754153,"heroId":49,"dotaPlus":{}},{"steamAccountId":137129583,"heroId":86,"dotaPlus":{"level":14}},{"steamAccountId":129958758,"heroId":16,"dotaPlus":{}},{"steamAccountId":157475523,"heroId":88,"dotaPlus":{}},{"steamAccountId":143693439,"heroId":66,"dotaPlus":{}}]}}
