{"match":{"startDateTime":1722308267,"chatEvents":[{"type":11,"fromHeroId":{},"toHeroId":{},"value":0},{"type":11,"fromHeroId":{},"toHeroId":{},"value":0},{"type":12,"fromHeroId":{},"toHeroId":{},"value":0},{"type":12,"fromHeroId":{},"toHeroId":{},"value":0},{"type":12,"fromHeroId":{},"toHeroId":{},"value":0},{"type":117,"fromHeroId":58,"toHeroId":{},"value":3},{"type":117,"fromHeroId":110,"toHeroId":{},"value":2},{"type":12,"fromHeroId":{},"toHeroId":{},"value":0},{"type":11,"fromHeroId":{},"toHeroId":{},"value":0},{"type":117,"fromHeroId":71,"toHeroId":{},"value":2},{"type":117,"fromHeroId":55,"toHeroId":{},"value":3},{"type":15,"fromHeroId":120,"toHeroId":{},"value":0},{"type":15,"fromHeroId":49,"toHeroId":{},"value":0},{"type":15,"fromHeroId":16,"toHeroId":{},"value":0},{"type":15,"fromHeroId":114,"toHeroId":{},"value":0},{"type":15,"fromHeroId":58,"toHeroId":{},"value":0},{"type":15,"fromHeroId":110,"toHeroId":{},"value":0},{"type":15,"fromHeroId":136,"toHeroId":{},"value":0},{"type":15,"fromHeroId":71,"toHeroId":{},"value":0},{"type":15,"fromHeroId":55,"toHeroId":{},"value":0},{"type":15,"fromHeroId":21,"toHeroId":{},"value":0}],"players":[{"steamAccountId":170896543,"heroId":49,"dotaPlus":{},"playbackData":{"runeEvents":[{"time":0,"rune":"BOUNTY","action":"PICKUP"},{"time":1262,"rune":"WISDOM","action":"PICKUP"},{"time":1696,"rune":"WISDOM","action":"PICKUP"},{"time":2100,"rune":"WISDOM","action":"PICKUP"}],"killEvents":[{"time":915,"isSmoke":false,"isRuneEffected":false},{"time":2173,"isSmoke":false,"isRuneEffected":false},{"time":2179,"isSmoke":false,"isRuneEffected":false},{"time":2359,"isSmoke":false,"isRuneEffected":false},{"time":2368,"isSmoke":false,"isRuneEffected":false},{"time":2382,"isSmoke":false,"isRuneEffected":false},{"time":2388,"isSmoke":false,"isRuneEffected":false}]}},{"steamAccountId":179313961,"heroId":16,"dotaPlus":{"level":11},"playbackData":{"runeEvents":[{"time":122,"rune":"WATER","action":"BOTTLE"},{"time":129,"rune":"WATER","action":"PICKUP"},{"time":134,"rune":"WATER","action":"BOTTLE"},{"time":159,"rune":"WATER","action":"PICKUP"},{"time":361,"rune":"REGEN","action":"BOTTLE"},{"time":388,"rune":"REGEN","action":"PICKUP"},{"time":841,"rune":"WISDOM","action":"BOTTLE"},{"time":841,"rune":"WISDOM","action":"PICKUP"},{"time":1212,"rune":"SHIELD","action":"BOTTLE"},{"time":1241,"rune":"SHIELD","action":"PICKUP"},{"time":1570,"rune":"REGEN","action":"BOTTLE"},{"time":1571,"rune":"REGEN","action":"PICKUP"},{"time":2280,"rune":"HASTE","action":"PICKUP"},{"time":2282,"rune":"SHIELD","action":"BOTTLE"},{"time":2326,"rune":"SHIELD","action":"PICKUP"}],"killEvents":[{"time":713,"isSmoke":false,"isRuneEffected":false},{"time":926,"isSmoke":false,"isRuneEffected":false},{"time":1150,"isSmoke":false,"isRuneEffected":false},{"time":1155,"isSmoke":false,"isRuneEffected":false},{"time":1532,"isSmoke":false,"isRuneEffected":false},{"time":1552,"isSmoke":false,"isRuneEffected":false},{"time":2065,"isSmoke":false,"isRuneEffected":false},{"time":2198,"isSmoke":false,"isRuneEffected":false}]}},{"steamAccountId":139031324,"heroId":21,"dotaPlus":{"level":20},"playbackData":{"runeEvents":[{"time":1,"rune":"BOUNTY","action":"PICKUP"}],"killEvents":[{"time":332,"isSmoke":false,"isRuneEffected":false},{"time":904,"isSmoke":true,"isRuneEffected":false},{"time":1169,"isSmoke":false,"isRuneEffected":false},{"time":1193,"isSmoke":false,"isRuneEffected":false},{"time":1532,"isSmoke":false,"isRuneEffected":false},{"time":1606,"isSmoke":false,"isRuneEffected":false},{"time":2219,"isSmoke":false,"isRuneEffected":false},{"time":2372,"isSmoke":false,"isRuneEffected":false}]}},{"steamAccountId":193884241,"heroId":71,"dotaPlus":{},"playbackData":{"runeEvents":[{"time":1,"rune":"BOUNTY","action":"PICKUP"},{"time":485,"rune":"INVISIBILITY","action":"PICKUP"},{"time":939,"rune":"BOUNTY","action":"PICKUP"}],"killEvents":[{"time":570,"isSmoke":false,"isRuneEffected":false}]}},{"steamAccountId":249835593,"heroId":110,"dotaPlus":{"level":21},"playbackData":{"runeEvents":[],"killEvents":[{"time":430,"isSmoke":false,"isRuneEffected":false},{"time":1165,"isSmoke":false,"isRuneEffected":false},{"time":1536,"isSmoke":false,"isRuneEffected":false},{"time":1644,"isSmoke":false,"isRuneEffected":false},{"time":1656,"isSmoke":false,"isRuneEffected":false}]}},{"steamAccountId":93817671,"heroId":58,"dotaPlus":{"level":11},"playbackData":{"runeEvents":[{"time":547,"rune":"BOUNTY","action":"PICKUP"},{"time":1280,"rune":"BOUNTY","action":"PICKUP"},{"time":1635,"rune":"BOUNTY","action":"PICKUP"},{"time":1837,"rune":"BOUNTY","action":"PICKUP"}],"killEvents":[{"time":516,"isSmoke":false,"isRuneEffected":false},{"time":590,"isSmoke":false,"isRuneEffected":false},{"time":1334,"isSmoke":false,"isRuneEffected":false}]}},{"steamAccountId":392169957,"heroId":120,"dotaPlus":{"level":13},"playbackData":{"runeEvents":[{"time":0,"rune":"BOUNTY","action":"PICKUP"},{"time":200,"rune":"BOUNTY","action":"BOTTLE"},{"time":200,"rune":"BOUNTY","action":"PICKUP"},{"time":243,"rune":"WATER","action":"BOTTLE"},{"time":248,"rune":"WATER","action":"PICKUP"},{"time":369,"rune":"BOUNTY","action":"BOTTLE"},{"time":369,"rune":"BOUNTY","action":"PICKUP"},{"time":546,"rune":"BOUNTY","action":"BOTTLE"},{"time":546,"rune":"BOUNTY","action":"PICKUP"},{"time":602,"rune":"HASTE","action":"BOTTLE"},{"time":639,"rune":"HASTE","action":"PICKUP"},{"time":728,"rune":"ILLUSION","action":"BOTTLE"},{"time":777,"rune":"ILLUSION","action":"PICKUP"},{"time":848,"rune":"SHIELD","action":"BOTTLE"},{"time":894,"rune":"SHIELD","action":"PICKUP"},{"time":971,"rune":"DOUBLE_DAMAGE","action":"BOTTLE"},{"time":1000,"rune":"DOUBLE_DAMAGE","action":"PICKUP"},{"time":1088,"rune":"ARCANE","action":"BOTTLE"},{"time":1096,"rune":"BOUNTY","action":"PICKUP"},{"time":1134,"rune":"ARCANE","action":"PICKUP"},{"time":1321,"rune":"ARCANE","action":"BOTTLE"},{"time":1324,"rune":"ARCANE","action":"PICKUP"},{"time":1449,"rune":"INVISIBILITY","action":"BOTTLE"},{"time":1454,"rune":"INVISIBILITY","action":"PICKUP"},{"time":1821,"rune":"HASTE","action":"PICKUP"},{"time":1836,"rune":"BOUNTY","action":"PICKUP"},{"time":1924,"rune":"ILLUSION","action":"BOTTLE"},{"time":2002,"rune":"ILLUSION","action":"PICKUP"},{"time":2098,"rune":"BOUNTY","action":"PICKUP"}],"killEvents":[{"time":931,"isSmoke":false,"isRuneEffected":false},{"time":949,"isSmoke":false,"isRuneEffected":false},{"time":1035,"isSmoke":false,"isRuneEffected":true},{"time":1151,"isSmoke":false,"isRuneEffected":true},{"time":1165,"isSmoke":false,"isRuneEffected":true},{"time":1478,"isSmoke":false,"isRuneEffected":true},{"time":1760,"isSmoke":true,"isRuneEffected":false},{"time":2059,"isSmoke":true,"isRuneEffected":false}]}},{"steamAccountId":835864135,"heroId":55,"dotaPlus":{"level":23},"playbackData":{"runeEvents":[{"time":864,"rune":"BOUNTY","action":"PICKUP"},{"time":1265,"rune":"BOUNTY","action":"PICKUP"},{"time":1265,"rune":"BOUNTY","action":"PICKUP"},{"time":1266,"rune":"BOUNTY","action":"PICKUP"}],"killEvents":[{"time":926,"isSmoke":false,"isRuneEffected":false},{"time":1043,"isSmoke":false,"isRuneEffected":false},{"time":1305,"isSmoke":false,"isRuneEffected":false}]}},{"steamAccountId":111030315,"heroId":114,"dotaPlus":{"level":15},"playbackData":{"runeEvents":[{"time":226,"rune":"BOUNTY","action":"PICKUP"},{"time":241,"rune":"WATER","action":"PICKUP"},{"time":369,"rune":"BOUNTY","action":"PICKUP"},{"time":420,"rune":"WISDOM","action":"PICKUP"},{"time":462,"rune":"WISDOM","action":"PICKUP"},{"time":726,"rune":"BOUNTY","action":"PICKUP"},{"time":954,"rune":"WISDOM","action":"PICKUP"},{"time":1446,"rune":"BOUNTY","action":"PICKUP"},{"time":1558,"rune":"BOUNTY","action":"PICKUP"},{"time":1702,"rune":"BOUNTY","action":"PICKUP"},{"time":2156,"rune":"BOUNTY","action":"PICKUP"},{"time":2163,"rune":"BOUNTY","action":"PICKUP"}],"killEvents":[{"time":1746,"isSmoke":true,"isRuneEffected":false}]}},{"steamAccountId":167976729,"heroId":136,"dotaPlus":{},"playbackData":{"runeEvents":[{"time":1260,"rune":"WISDOM","action":"PICKUP"},{"time":1690,"rune":"WISDOM","action":"PICKUP"},{"time":1723,"rune":"DOUBLE_DAMAGE","action":"BOTTLE"},{"time":1742,"rune":"DOUBLE_DAMAGE","action":"PICKUP"},{"time":2090,"rune":"DOUBLE_DAMAGE","action":"BOTTLE"},{"time":2124,"rune":"WISDOM","action":"PICKUP"},{"time":2172,"rune":"DOUBLE_DAMAGE","action":"PICKUP"}],"killEvents":[{"time":510,"isSmoke":false,"isRuneEffected":false},{"time":667,"isSmoke":false,"isRuneEffected":false},{"time":783,"isSmoke":true,"isRuneEffected":false},{"time":1419,"isSmoke":false,"isRuneEffected":false},{"time":1750,"isSmoke":true,"isRuneEffected":true},{"time":1758,"isSmoke":true,"isRuneEffected":true},{"time":1901,"isSmoke":false,"isRuneEffected":false},{"time":2176,"isSmoke":false,"isRuneEffected":true}]}}]}}
