{"match":{"startDateTime":1724004002,"chatEvents":[{"type":1000,"fromHeroId":69,"toHeroId":137,"value":50},{"type":1000,"fromHeroId":137,"toHeroId":69,"value":50},{"type":34,"fromHeroId":64,"toHeroId":{},"value":0},{"type":36,"fromHeroId":16,"toHeroId":{},"value":0},{"type":34,"fromHeroId":82,"toHeroId":{},"value":0},{"type":15,"fromHeroId":82,"toHeroId":{},"value":0},{"type":1000,"fromHeroId":52,"toHeroId":69,"value":50},{"type":19,"fromHeroId":82,"toHeroId":{},"value":0},{"type":15,"fromHeroId":82,"toHeroId":{},"value":0},{"type":19,"fromHeroId":82,"toHeroId":{},"value":0},{"type":36,"fromHeroId":16,"toHeroId":{},"value":0},{"type":5,"fromHeroId":16,"toHeroId":{},"value":369},{"type":11,"fromHeroId":{},"toHeroId":{},"value":0},{"type":12,"fromHeroId":{},"toHeroId":{},"value":0},{"type":12,"fromHeroId":{},"toHeroId":{},"value":0},{"type":11,"fromHeroId":{},"toHeroId":{},"value":0},{"type":12,"fromHeroId":{},"toHeroId":{},"value":0},{"type":12,"fromHeroId":{},"toHeroId":{},"value":0},{"type":12,"fromHeroId":{},"toHeroId":{},"value":0},{"type":12,"fromHeroId":{},"toHeroId":{},"value":0},{"type":117,"fromHeroId":35,"toHeroId":{},"value":3},{"type":12,"fromHeroId":{},"toHeroId":{},"value":0},{"type":114,"fromHeroId":82,"toHeroId":{},"value":2},{"type":12,"fromHeroId":{},"toHeroId":{},"value":0},{"type":1000,"fromHeroId":49,"toHeroId":82,"value":50},{"type":15,"fromHeroId":82,"toHeroId":{},"value":0},{"type":15,"fromHeroId":57,"toHeroId":{},"value":0},{"type":15,"fromHeroId":137,"toHeroId":{},"value":0},{"type":15,"fromHeroId":16,"toHeroId":{},"value":0},{"type":15,"fromHeroId":52,"toHeroId":{},"value":0},{"type":15,"fromHeroId":69,"toHeroId":{},"value":0},{"type":15,"fromHeroId":9,"toHeroId":{},"value":0},{"type":15,"fromHeroId":64,"toHeroId":{},"value":0},{"type":15,"fromHeroId":49,"toHeroId":{},"value":0},{"type":15,"fromHeroId":35,"toHeroId":{},"value":0},{"type":11,"fromHeroId":{},"toHeroId":{},"value":0}],"players":[{"steamAccountId":140297552,"heroId":16,"dotaPlus":{},"playbackData":{"runeEvents":[{"time":0,"rune":"BOUNTY","action":"PICKUP"},{"time":142,"rune":"WATER","action":"BOTTLE"},{"time":211,"rune":"WATER","action":"PICKUP"},{"time":249,"rune":"WATER","action":"BOTTLE"},{"time":250,"rune":"WATER","action":"PICKUP"},{"time":286,"rune":"BOUNTY","action":"BOTTLE"},{"time":286,"rune":"BOUNTY","action":"PICKUP"},{"time":362,"rune":"HASTE","action":"BOTTLE"},{"time":412,"rune":"HASTE","action":"PICKUP"},{"time":550,"rune":"BOUNTY","action":"BOTTLE"},{"time":550,"rune":"BOUNTY","action":"PICKUP"},{"time":562,"rune":"WATER","action":"BOTTLE"},{"time":621,"rune":"WATER","action":"PICKUP"},{"time":625,"rune":"WATER","action":"BOTTLE"},{"time":652,"rune":"WATER","action":"PICKUP"},{"time":723,"rune":"DOUBLE_DAMAGE","action":"BOTTLE"},{"time":751,"rune":"DOUBLE_DAMAGE","action":"PICKUP"},{"time":773,"rune":"BOUNTY","action":"BOTTLE"},{"time":773,"rune":"BOUNTY","action":"PICKUP"},{"time":908,"rune":"WISDOM","action":"BOTTLE"},{"time":909,"rune":"WISDOM","action":"PICKUP"},{"time":957,"rune":"BOUNTY","action":"BOTTLE"},{"time":957,"rune":"BOUNTY","action":"PICKUP"},{"time":1135,"rune":"WATER","action":"BOTTLE"},{"time":1135,"rune":"WATER","action":"PICKUP"}],"killEvents":[{"time":847,"isSmoke":true,"isRuneEffected":false}]}},{"steamAccountId":152168157,"heroId":52,"dotaPlus":{},"playbackData":{"runeEvents":[{"time":420,"rune":"WISDOM","action":"PICKUP"},{"time":760,"rune":"BOUNTY","action":"PICKUP"},{"time":1208,"rune":"BOUNTY","action":"PICKUP"},{"time":1303,"rune":"BOUNTY","action":"PICKUP"},{"time":1325,"rune":"SHIELD","action":"PICKUP"}],"killEvents":[{"time":253,"isSmoke":false,"isRuneEffected":false},{"time":424,"isSmoke":false,"isRuneEffected":false},{"time":497,"isSmoke":false,"isRuneEffected":false},{"time":677,"isSmoke":true,"isRuneEffected":false}]}},{"steamAccountId":73401082,"heroId":64,"dotaPlus":{"level":18},"playbackData":{"runeEvents":[{"time":0,"rune":"BOUNTY","action":"PICKUP"},{"time":843,"rune":"ARCANE","action":"PICKUP"},{"time":1118,"rune":"INVISIBILITY","action":"PICKUP"}],"killEvents":[{"time":193,"isSmoke":false,"isRuneEffected":false},{"time":367,"isSmoke":false,"isRuneEffected":false},{"time":395,"isSmoke":false,"isRuneEffected":false},{"time":1588,"isSmoke":false,"isRuneEffected":false}]}},{"steamAccountId":203351055,"heroId":69,"dotaPlus":{"level":14},"playbackData":{"runeEvents":[{"time":903,"rune":"BOUNTY","action":"PICKUP"}],"killEvents":[{"time":426,"isSmoke":false,"isRuneEffected":false}]}},{"steamAccountId":96183976,"heroId":82,"dotaPlus":{"level":14},"playbackData":{"runeEvents":[{"time":384,"rune":"BOUNTY","action":"PICKUP"},{"time":1461,"rune":"BOUNTY","action":"PICKUP"}],"killEvents":[{"time":1485,"isSmoke":true,"isRuneEffected":false}]}},{"steamAccountId":148215639,"heroId":9,"dotaPlus":{},"playbackData":{"runeEvents":[{"time":3,"rune":"BOUNTY","action":"PICKUP"},{"time":709,"rune":"BOUNTY","action":"PICKUP"},{"time":725,"rune":"BOUNTY","action":"PICKUP"},{"time":966,"rune":"ILLUSION","action":"PICKUP"},{"time":1260,"rune":"WISDOM","action":"PICKUP"}],"killEvents":[{"time":697,"isSmoke":false,"isRuneEffected":false},{"time":876,"isSmoke":false,"isRuneEffected":false},{"time":1065,"isSmoke":false,"isRuneEffected":false},{"time":1484,"isSmoke":false,"isRuneEffected":false},{"time":1491,"isSmoke":false,"isRuneEffected":false},{"time":1600,"isSmoke":false,"isRuneEffected":false}]}},{"steamAccountId":173978074,"heroId":49,"dotaPlus":{"level":12},"playbackData":{"runeEvents":[{"time":131,"rune":"WATER","action":"PICKUP"},{"time":267,"rune":"WATER","action":"PICKUP"},{"time":601,"rune":"SHIELD","action":"PICKUP"},{"time":910,"rune":"BOUNTY","action":"PICKUP"},{"time":1218,"rune":"HASTE","action":"PICKUP"},{"time":1260,"rune":"WISDOM","action":"PICKUP"},{"time":1387,"rune":"BOUNTY","action":"PICKUP"}],"killEvents":[{"time":77,"isSmoke":false,"isRuneEffected":false},{"time":868,"isSmoke":false,"isRuneEffected":false},{"time":944,"isSmoke":false,"isRuneEffected":false},{"time":994,"isSmoke":false,"isRuneEffected":false},{"time":1143,"isSmoke":false,"isRuneEffected":false},{"time":1367,"isSmoke":false,"isRuneEffected":false},{"time":1509,"isSmoke":false,"isRuneEffected":false},{"time":1592,"isSmoke":false,"isRuneEffected":false},{"time":1593,"isSmoke":false,"isRuneEffected":false}]}},{"steamAccountId":138857296,"heroId":137,"dotaPlus":{"level":23},"playbackData":{"runeEvents":[{"time":1134,"rune":"BOUNTY","action":"PICKUP"}],"killEvents":[{"time":422,"isSmoke":false,"isRuneEffected":false},{"time":439,"isSmoke":false,"isRuneEffected":false},{"time":493,"isSmoke":false,"isRuneEffected":false},{"time":1008,"isSmoke":false,"isRuneEffected":false},{"time":1046,"isSmoke":false,"isRuneEffected":false},{"time":1061,"isSmoke":false,"isRuneEffected":false},{"time":1383,"isSmoke":false,"isRuneEffected":false}]}},{"steamAccountId":207829314,"heroId":35,"dotaPlus":{},"playbackData":{"runeEvents":[{"time":840,"rune":"WISDOM","action":"PICKUP"}],"killEvents":[{"time":1499,"isSmoke":false,"isRuneEffected":false},{"time":1589,"isSmoke":false,"isRuneEffected":false}]}},{"steamAccountId":94296097,"heroId":57,"dotaPlus":{},"playbackData":{"runeEvents":[{"time":0,"rune":"BOUNTY","action":"PICKUP"},{"time":420,"rune":"WISDOM","action":"PICKUP"},{"time":480,"rune":"REGEN","action":"PICKUP"},{"time":524,"rune":"BOUNTY","action":"PICKUP"},{"time":524,"rune":"BOUNTY","action":"PICKUP"},{"time":1018,"rune":"BOUNTY","action":"PICKUP"}],"killEvents":[{"time":337,"isSmoke":false,"isRuneEffected":false},{"time":1102,"isSmoke":false,"isRuneEffected":false},{"time":1408,"isSmoke":false,"isRuneEffected":false}]}}]}}
