{"match":{"startDateTime":1725536183,"chatEvents":[{"type":1004,"fromHeroId":38,"toHeroId":{},"value":74},{"type":1004,"fromHeroId":90,"toHeroId":{},"value":67},{"type":1004,"fromHeroId":71,"toHeroId":{},"value":124},{"type":1004,"fromHeroId":57,"toHeroId":{},"value":74},{"type":1004,"fromHeroId":63,"toHeroId":{},"value":226},{"type":1004,"fromHeroId":26,"toHeroId":{},"value":74},{"type":1000,"fromHeroId":38,"toHeroId":98,"value":50},{"type":1000,"fromHeroId":98,"toHeroId":38,"value":50},{"type":34,"fromHeroId":57,"toHeroId":{},"value":0},{"type":36,"fromHeroId":19,"toHeroId":{},"value":0},{"type":5,"fromHeroId":63,"toHeroId":{},"value":390},{"type":12,"fromHeroId":{},"toHeroId":{},"value":0},{"type":12,"fromHeroId":{},"toHeroId":{},"value":0},{"type":117,"fromHeroId":90,"toHeroId":{},"value":2},{"type":117,"fromHeroId":57,"toHeroId":{},"value":3},{"type":12,"fromHeroId":{},"toHeroId":{},"value":0},{"type":12,"fromHeroId":{},"toHeroId":{},"value":0},{"type":34,"fromHeroId":57,"toHeroId":{},"value":0},{"type":36,"fromHeroId":19,"toHeroId":{},"value":0},{"type":1000,"fromHeroId":19,"toHeroId":90,"value":50},{"type":1000,"fromHeroId":90,"toHeroId":19,"value":50},{"type":12,"fromHeroId":{},"toHeroId":{},"value":0},{"type":1000,"fromHeroId":38,"toHeroId":21,"value":50},{"type":12,"fromHeroId":{},"toHeroId":{},"value":0},{"type":117,"fromHeroId":17,"toHeroId":{},"value":3},{"type":11,"fromHeroId":{},"toHeroId":{},"value":0},{"type":117,"fromHeroId":63,"toHeroId":{},"value":3},{"type":91,"fromHeroId":57,"toHeroId":{},"value":0},{"type":12,"fromHeroId":{},"toHeroId":{},"value":0},{"type":119,"fromHeroId":90,"toHeroId":{},"value":0},{"type":12,"fromHeroId":{},"toHeroId":{},"value":0},{"type":15,"fromHeroId":90,"toHeroId":{},"value":0},{"type":1000,"fromHeroId":98,"toHeroId":90,"value":50},{"type":15,"fromHeroId":19,"toHeroId":{},"value":0},{"type":15,"fromHeroId":71,"toHeroId":{},"value":0},{"type":15,"fromHeroId":21,"toHeroId":{},"value":0},{"type":15,"fromHeroId":63,"toHeroId":{},"value":0},{"type":15,"fromHeroId":38,"toHeroId":{},"value":0},{"type":15,"fromHeroId":98,"toHeroId":{},"value":0},{"type":15,"fromHeroId":57,"toHeroId":{},"value":0},{"type":15,"fromHeroId":26,"toHeroId":{},"value":0}],"players":[{"steamAccountId":124801257,"heroId":21,"dotaPlus":{"level":11},"playbackData":{"runeEvents":[{"time":1263,"rune":"BOUNTY","action":"PICKUP"},{"time":2177,"rune":"DOUBLE_DAMAGE","action":"PICKUP"}],"killEvents":[{"time":558,"isSmoke":false,"isRuneEffected":false},{"time":580,"isSmoke":false,"isRuneEffected":false},{"time":1202,"isSmoke":false,"isRuneEffected":false},{"time":1218,"isSmoke":false,"isRuneEffected":false},{"time":1226,"isSmoke":false,"isRuneEffected":false},{"time":1372,"isSmoke":true,"isRuneEffected":false},{"time":1514,"isSmoke":false,"isRuneEffected":false},{"time":1704,"isSmoke":true,"isRuneEffected":false},{"time":1739,"isSmoke":false,"isRuneEffected":false},{"time":1747,"isSmoke":false,"isRuneEffected":false},{"time":1749,"isSmoke":false,"isRuneEffected":false},{"time":2192,"isSmoke":false,"isRuneEffected":true},{"time":2273,"isSmoke":false,"isRuneEffected":false}]}},{"steamAccountId":480412663,"heroId":19,"dotaPlus":{"level":18},"playbackData":{"runeEvents":[{"time":138,"rune":"WATER","action":"BOTTLE"},{"time":139,"rune":"WATER","action":"PICKUP"},{"time":240,"rune":"WATER","action":"BOTTLE"},{"time":242,"rune":"WATER","action":"PICKUP"},{"time":360,"rune":"REGEN","action":"BOTTLE"},{"time":417,"rune":"REGEN","action":"PICKUP"},{"time":489,"rune":"ILLUSION","action":"BOTTLE"},{"time":538,"rune":"ILLUSION","action":"PICKUP"},{"time":1274,"rune":"WISDOM","action":"BOTTLE"},{"time":1278,"rune":"WISDOM","action":"PICKUP"},{"time":1565,"rune":"SHIELD","action":"BOTTLE"},{"time":1615,"rune":"SHIELD","action":"PICKUP"}],"killEvents":[{"time":548,"isSmoke":false,"isRuneEffected":false},{"time":561,"isSmoke":false,"isRuneEffected":false},{"time":865,"isSmoke":false,"isRuneEffected":false},{"time":872,"isSmoke":false,"isRuneEffected":false},{"time":1353,"isSmoke":true,"isRuneEffected":false},{"time":1688,"isSmoke":true,"isRuneEffected":false},{"time":1712,"isSmoke":false,"isRuneEffected":false},{"time":1779,"isSmoke":false,"isRuneEffected":false},{"time":1909,"isSmoke":false,"isRuneEffected":false}]}},{"steamAccountId":165564598,"heroId":38,"dotaPlus":{"level":30},"playbackData":{"runeEvents":[],"killEvents":[{"time":1216,"isSmoke":false,"isRuneEffected":false},{"time":1496,"isSmoke":true,"isRuneEffected":false},{"time":1857,"isSmoke":false,"isRuneEffected":false},{"time":2634,"isSmoke":true,"isRuneEffected":false}]}},{"steamAccountId":317880638,"heroId":90,"dotaPlus":{"level":25},"playbackData":{"runeEvents":[{"time":0,"rune":"BOUNTY","action":"PICKUP"},{"time":419,"rune":"WISDOM","action":"PICKUP"},{"time":840,"rune":"WISDOM","action":"PICKUP"}],"killEvents":[{"time":233,"isSmoke":false,"isRuneEffected":false},{"time":247,"isSmoke":false,"isRuneEffected":false},{"time":2336,"isSmoke":false,"isRuneEffected":false}]}},{"steamAccountId":431770905,"heroId":71,"dotaPlus":{},"playbackData":{"runeEvents":[{"time":239,"rune":"WATER","action":"PICKUP"},{"time":375,"rune":"BOUNTY","action":"PICKUP"},{"time":783,"rune":"BOUNTY","action":"PICKUP"},{"time":897,"rune":"BOUNTY","action":"PICKUP"},{"time":933,"rune":"BOUNTY","action":"PICKUP"},{"time":1101,"rune":"BOUNTY","action":"PICKUP"},{"time":1281,"rune":"BOUNTY","action":"PICKUP"},{"time":1550,"rune":"BOUNTY","action":"PICKUP"},{"time":1771,"rune":"WISDOM","action":"PICKUP"},{"time":2050,"rune":"BOUNTY","action":"PICKUP"},{"time":2064,"rune":"SHIELD","action":"BOTTLE"},{"time":2112,"rune":"WISDOM","action":"PICKUP"},{"time":2153,"rune":"SHIELD","action":"PICKUP"},{"time":2320,"rune":"HASTE","action":"PICKUP"},{"time":2377,"rune":"BOUNTY","action":"PICKUP"},{"time":2424,"rune":"REGEN","action":"PICKUP"},{"time":2431,"rune":"BOUNTY","action":"PICKUP"},{"time":2528,"rune":"WISDOM","action":"PICKUP"}],"killEvents":[{"time":1365,"isSmoke":false,"isRuneEffected":false},{"time":2164,"isSmoke":false,"isRuneEffected":false}]}},{"steamAccountId":10366616,"heroId":57,"dotaPlus":{"level":15},"playbackData":{"runeEvents":[{"time":6,"rune":"BOUNTY","action":"PICKUP"},{"time":360,"rune":"BOUNTY","action":"PICKUP"},{"time":720,"rune":"BOUNTY","action":"PICKUP"},{"time":1476,"rune":"BOUNTY","action":"PICKUP"},{"time":2216,"rune":"BOUNTY","action":"PICKUP"},{"time":2217,"rune":"BOUNTY","action":"PICKUP"},{"time":2217,"rune":"BOUNTY","action":"PICKUP"},{"time":2217,"rune":"BOUNTY","action":"PICKUP"}],"killEvents":[{"time":450,"isSmoke":false,"isRuneEffected":false}]}},{"steamAccountId":100058342,"heroId":63,"dotaPlus":{"level":18},"playbackData":{"runeEvents":[{"time":960,"rune":"HASTE","action":"PICKUP"},{"time":997,"rune":"BOUNTY","action":"PICKUP"},{"time":997,"rune":"BOUNTY","action":"PICKUP"},{"time":1085,"rune":"BOUNTY","action":"PICKUP"},{"time":1804,"rune":"REGEN","action":"PICKUP"},{"time":1811,"rune":"BOUNTY","action":"PICKUP"},{"time":1811,"rune":"BOUNTY","action":"PICKUP"}],"killEvents":[{"time":551,"isSmoke":false,"isRuneEffected":false},{"time":801,"isSmoke":false,"isRuneEffected":false},{"time":1021,"isSmoke":false,"isRuneEffected":false},{"time":2650,"isSmoke":false,"isRuneEffected":false},{"time":2670,"isSmoke":false,"isRuneEffected":false}]}},{"steamAccountId":898455820,"heroId":17,"dotaPlus":{"level":28},"playbackData":{"runeEvents":[{"time":137,"rune":"WATER","action":"BOTTLE"},{"time":138,"rune":"WATER","action":"PICKUP"},{"time":269,"rune":"BOUNTY","action":"BOTTLE"},{"time":269,"rune":"BOUNTY","action":"PICKUP"},{"time":608,"rune":"ARCANE","action":"BOTTLE"},{"time":638,"rune":"ARCANE","action":"PICKUP"},{"time":733,"rune":"DOUBLE_DAMAGE","action":"BOTTLE"},{"time":823,"rune":"DOUBLE_DAMAGE","action":"PICKUP"},{"time":1081,"rune":"SHIELD","action":"BOTTLE"},{"time":1133,"rune":"SHIELD","action":"PICKUP"},{"time":1202,"rune":"INVISIBILITY","action":"BOTTLE"},{"time":1202,"rune":"INVISIBILITY","action":"PICKUP"},{"time":1386,"rune":"HASTE","action":"BOTTLE"},{"time":1395,"rune":"BOUNTY","action":"PICKUP"},{"time":1449,"rune":"HASTE","action":"PICKUP"},{"time":1475,"rune":"ARCANE","action":"BOTTLE"},{"time":1490,"rune":"ARCANE","action":"PICKUP"},{"time":1681,"rune":"WISDOM","action":"PICKUP"},{"time":1924,"rune":"ILLUSION","action":"BOTTLE"},{"time":1924,"rune":"ILLUSION","action":"PICKUP"},{"time":2101,"rune":"WISDOM","action":"PICKUP"},{"time":2530,"rune":"WISDOM","action":"PICKUP"}],"killEvents":[{"time":867,"isSmoke":true,"isRuneEffected":true},{"time":1147,"isSmoke":false,"isRuneEffected":false},{"time":1694,"isSmoke":true,"isRuneEffected":false},{"time":2158,"isSmoke":false,"isRuneEffected":false},{"time":2410,"isSmoke":false,"isRuneEffected":false},{"time":2640,"isSmoke":true,"isRuneEffected":false},{"time":2652,"isSmoke":false,"isRuneEffected":false},{"time":2661,"isSmoke":false,"isRuneEffected":false},{"time":2665,"isSmoke":false,"isRuneEffected":false},{"time":2709,"isSmoke":false,"isRuneEffected":false}]}},{"steamAccountId":183719386,"heroId":98,"dotaPlus":{"level":30},"playbackData":{"runeEvents":[{"time":0,"rune":"BOUNTY","action":"PICKUP"},{"time":573,"rune":"BOUNTY","action":"PICKUP"},{"time":611,"rune":"BOUNTY","action":"PICKUP"},{"time":846,"rune":"INVISIBILITY","action":"PICKUP"},{"time":2523,"rune":"ILLUSION","action":"PICKUP"},{"time":2550,"rune":"BOUNTY","action":"PICKUP"}],"killEvents":[{"time":403,"isSmoke":false,"isRuneEffected":false},{"time":445,"isSmoke":false,"isRuneEffected":false},{"time":498,"isSmoke":false,"isRuneEffected":false},{"time":656,"isSmoke":false,"isRuneEffected":false},{"time":670,"isSmoke":false,"isRuneEffected":false},{"time":873,"isSmoke":false,"isRuneEffected":false},{"time":1119,"isSmoke":true,"isRuneEffected":false},{"time":1145,"isSmoke":false,"isRuneEffected":false},{"time":1734,"isSmoke":false,"isRuneEffected":false},{"time":1843,"isSmoke":false,"isRuneEffected":false},{"time":1857,"isSmoke":false,"isRuneEffected":false},{"time":2162,"isSmoke":false,"isRuneEffected":false},{"time":2172,"isSmoke":false,"isRuneEffected":false},{"time":2338,"isSmoke":false,"isRuneEffected":false}]}},{"steamAccountId":25907144,"heroId":26,"dotaPlus":{"level":13},"playbackData":{"runeEvents":[{"time":1,"rune":"BOUNTY","action":"PICKUP"},{"time":266,"rune":"BOUNTY","action":"PICKUP"},{"time":420,"rune":"WISDOM","action":"PICKUP"},{"time":577,"rune":"BOUNTY","action":"PICKUP"},{"time":730,"rune":"BOUNTY","action":"PICKUP"},{"time":906,"rune":"WISDOM","action":"PICKUP"},{"time":987,"rune":"BOUNTY","action":"PICKUP"},{"time":1266,"rune":"WISDOM","action":"PICKUP"},{"time":2211,"rune":"BOUNTY","action":"PICKUP"}],"killEvents":[{"time":1350,"isSmoke":true,"isRuneEffected":false},{"time":1848,"isSmoke":false,"isRuneEffected":false},{"time":2338,"isSmoke":false,"isRuneEffected":false}]}}]}}
